tiatoolbox/__init__.py
tiatoolbox/__main__.py
tiatoolbox/enums.py
tiatoolbox/tiatoolbox.py
tiatoolbox/typing.py
tiatoolbox/annotation/__init__.py
tiatoolbox/annotation/dsl.py
tiatoolbox/annotation/storage.py
tiatoolbox/cli/__init__.py
tiatoolbox/cli/common.py
tiatoolbox/cli/nucleus_instance_segment.py
tiatoolbox/cli/patch_predictor.py
tiatoolbox/cli/read_bounds.py
tiatoolbox/cli/save_tiles.py
tiatoolbox/cli/semantic_segment.py
tiatoolbox/cli/show_wsi.py
tiatoolbox/cli/slide_info.py
tiatoolbox/cli/slide_thumbnail.py
tiatoolbox/cli/stain_norm.py
tiatoolbox/cli/tissue_mask.py
tiatoolbox/cli/visualize.py
tiatoolbox/data/__init__.py
tiatoolbox/data/pretrained_model.yaml
tiatoolbox/data/remote_samples.yaml
tiatoolbox/data/target_image.png
tiatoolbox/data/visualization/static/css/fontawesome-all.min.css
tiatoolbox/data/visualization/static/css/ol-ext.min.css
tiatoolbox/data/visualization/static/css/ol.css
tiatoolbox/data/visualization/static/js/ol-ext.min.js
tiatoolbox/data/visualization/static/js/ol.js
tiatoolbox/data/visualization/static/js/polyfill.min.js
tiatoolbox/data/visualization/static/webfonts/fa-brands-400.eot
tiatoolbox/data/visualization/static/webfonts/fa-brands-400.svg
tiatoolbox/data/visualization/static/webfonts/fa-brands-400.ttf
tiatoolbox/data/visualization/static/webfonts/fa-brands-400.woff
tiatoolbox/data/visualization/static/webfonts/fa-brands-400.woff2
tiatoolbox/data/visualization/static/webfonts/fa-regular-400.eot
tiatoolbox/data/visualization/static/webfonts/fa-regular-400.svg
tiatoolbox/data/visualization/static/webfonts/fa-regular-400.ttf
tiatoolbox/data/visualization/static/webfonts/fa-regular-400.woff
tiatoolbox/data/visualization/static/webfonts/fa-regular-400.woff2
tiatoolbox/data/visualization/static/webfonts/fa-solid-900.eot
tiatoolbox/data/visualization/static/webfonts/fa-solid-900.svg
tiatoolbox/data/visualization/static/webfonts/fa-solid-900.ttf
tiatoolbox/data/visualization/static/webfonts/fa-solid-900.woff
tiatoolbox-1.6.0.dist-info/AUTHORS.md
tiatoolbox-1.6.0.dist-info/LICENSE
tiatoolbox-1.6.0.dist-info/METADATA
tiatoolbox-1.6.0.dist-info/WHEEL
tiatoolbox-1.6.0.dist-info/dependency_links.txt
tiatoolbox-1.6.0.dist-info/entry_points.txt
tiatoolbox-1.6.0.dist-info/top_level.txt
tiatoolbox-1.6.0.dist-info/RECORD
