Metadata-Version: 2.1
Name: tiatoolbox
Version: 1.6.0
Summary: Computational pathology toolbox developed by TIA Centre.
Home-page: https://github.com/TissueImageAnalytics/tiatoolbox
Author: TIA Centre
Author-email: tia@dcs.warwick.ac.uk
Keywords: tiatoolbox
Classifier: Development Status :: 2 - Pre-Alpha
Classifier: Intended Audience :: Developers
Classifier: Natural Language :: English
Classifier: Programming Language :: Python :: 3
Classifier: Programming Language :: Python :: 3.9
Classifier: Programming Language :: Python :: 3.10
Classifier: Programming Language :: Python :: 3.11
Classifier: Programming Language :: Python :: 3.12
Requires-Python: >=3.9, <3.13
License-File: LICENSE
License-File: AUTHORS.md
Requires-Dist: albumentations<=1.4.21,>=1.3.0
Requires-Dist: bokeh<3.6.0,>=3.1.1
Requires-Dist: Click<=8.1.7,>=8.1.3
Requires-Dist: defusedxml<=0.7.1,>=0.7.1
Requires-Dist: filelock<=3.16.1,>=3.9.0
Requires-Dist: flask<=3.1.0,>=2.2.2
Requires-Dist: flask-cors<=5.0.0,>=4.0.0
Requires-Dist: glymur<=0.13.6,>=0.12.7
Requires-Dist: imagecodecs<=2024.9.22,>=2022.9.26
Requires-Dist: joblib<=1.4.2,>=1.1.1
Requires-Dist: jupyterlab<=4.3.2,>=3.5.2
Requires-Dist: matplotlib<=3.9.3,>=3.6.2
Requires-Dist: numba<=0.60.0,>=0.57.0
Requires-Dist: numpy<2.0.0,>=1.23.5
Requires-Dist: opencv-python<=4.10.0,>=4.6.0
Requires-Dist: openslide-python<=1.4.1,>=1.2.0
Requires-Dist: pandas<=2.2.3,>=2.0.0
Requires-Dist: pillow<=11.0.0,>=9.3.0
Requires-Dist: pydicom<=3.0.1,>=2.3.1
Requires-Dist: pyyaml<=6.0.2,>=6.0
Requires-Dist: requests<=2.32.3,>=2.28.1
Requires-Dist: scikit-image<=0.24.0,>=0.20
Requires-Dist: scikit-learn<=1.5.2,>=1.2.0
Requires-Dist: scipy<=1.14.1,>=1.8
Requires-Dist: shapely<=2.0.6,>=2.0.0
Requires-Dist: SimpleITK<=2.4.0,>=2.2.1
Requires-Dist: sphinx<=8.1.3,>=5.3.0
Requires-Dist: tifffile<=2024.9.20,>=2022.10.10
Requires-Dist: timm<=1.0.12,>=1.0.3
Requires-Dist: torch<=2.5.1,>=2.1.0
Requires-Dist: torchvision<=0.20.1,>=0.15.0
Requires-Dist: tqdm<=4.67.1,>=4.64.1
Requires-Dist: umap-learn<=0.5.7,>=0.5.3
Requires-Dist: wsidicom<=0.22.0,>=0.18.0
Requires-Dist: zarr<=2.18.3,>=2.13.3
